can_decoder/DBCLoader.py
can_decoder/DecoderBase.py
can_decoder/Frame.py
can_decoder/Signal.py
can_decoder/SignalDB.py
can_decoder/__init__.py
can_decoder/support.py
can_decoder/dataframe/DataFrameDecoder.py
can_decoder/dataframe/DataFrameGenericDecoder.py
can_decoder/dataframe/DataFrameJ1939Decoder.py
can_decoder/dataframe/__init__.py
can_decoder/exceptions/CANDecoderException.py
can_decoder/exceptions/DataSizeMismatchException.py
can_decoder/exceptions/__init__.py
can_decoder/iterator/DecodedSignal.py
can_decoder/iterator/IteratorDecoder.py
can_decoder/iterator/IteratorGenericDecoder.py
can_decoder/iterator/IteratorJ1939Decoder.py
can_decoder/iterator/__init__.py
can_decoder/iterator/can_record.py
can_decoder/warnings/CANDecoderWarning.py
can_decoder/warnings/DataSizeMismatchWarning.py
can_decoder/warnings/MissingDataWarning.py
can_decoder/warnings/__init__.py
can_decoder-0.1.9.dist-info/METADATA
can_decoder-0.1.9.dist-info/WHEEL
can_decoder-0.1.9.dist-info/licenses/LICENSE
can_decoder-0.1.9.dist-info/RECORD
