Metadata-Version: 2.1
Name: can_decoder
Version: 0.1.9
Summary: Utilities to decode CAN log files
Project-URL: Homepage, https://www.csselectronics.com/pages/python-can-bus-api#void
Project-URL: Repository, https://github.com/CSS-Electronics/can_decoder
Author-email: CSS Electronics <contact@csselectronics.com>
License-File: LICENSE
Classifier: License :: OSI Approved :: MIT License
Classifier: Operating System :: OS Independent
Classifier: Programming Language :: Python :: 3
Requires-Python: >=3.7
Requires-Dist: numpy
